maniphono/__init__.py
maniphono/common.py
maniphono/phonomodel.py
maniphono/segment.py
maniphono/segsequence.py
maniphono/sound.py
maniphono/models/encoder/graphemes.tsv
maniphono/models/mipa/model.csv
maniphono/models/mipa/sounds.csv
maniphono/models/tresoldi/model.csv
maniphono/models/tresoldi/sounds.csv
maniphono-0.4.1.dist-info/AUTHORS.md
maniphono-0.4.1.dist-info/LICENSE
maniphono-0.4.1.dist-info/METADATA
maniphono-0.4.1.dist-info/WHEEL
maniphono-0.4.1.dist-info/top_level.txt
maniphono-0.4.1.dist-info/RECORD
