Metadata-Version: 2.1
Name: maniphono
Version: 0.4.1
Summary: Python library for the symbolic manipulation of phoneme representations
Home-page: https://github.com/tresoldi/maniphono
Author: Tiago Tresoldi
Author-email: tiago.tresoldi@lingfil.uu.se
License: MIT
Keywords: phoneme,phonology,phonetics,distinctive features,machine learning
Classifier: License :: OSI Approved :: MIT License
Classifier: Operating System :: OS Independent
Classifier: Programming Language :: Python :: 3
Classifier: Topic :: Software Development :: Libraries
Requires-Python: >=3.7
License-File: LICENSE
License-File: AUTHORS.md
